majestic/__main__.py
majestic/core/__init__.py
majestic-0.2601.0.dist-info/METADATA
majestic-0.2601.0.dist-info/WHEEL
majestic-0.2601.0.dist-info/top_level.txt
majestic-0.2601.0.dist-info/RECORD
