Metadata-Version: 2.4
Name: majestic
Version: 0.2601.0
Summary: No frontiers, true fullstack.
Author-email: Kairix Devteam <devteam@kairix.dev>
Requires-Python: >=3.12
